h2lib/HAWC2Lib.dll
h2lib/__init__.py
h2lib/_h2lib.py
h2lib/_version.py
h2lib/distributed_sections.py
h2lib/dll_wrapper.py
h2lib/h2lib_signatures.py
h2lib-13.2.901.dist-info/METADATA
h2lib-13.2.901.dist-info/WHEEL
h2lib-13.2.901.dist-info/top_level.txt
h2lib-13.2.901.dist-info/RECORD
