Metadata-Version: 2.4
Name: h2lib
Version: 13.2.901
Summary: Python interface to HAWC2 (13.2.9+4-gfd77867)
Download-URL: 
Author: Mads M. Pedersen, S.G.Horcas and N.G.Ramos
Author-email: mmpe@dtu.dk
Maintainer: 
Maintainer-email: 
Project-URL: Documentation, https://hawc2.pages.windenergy.dtu.dk/HAWC2Lib/
Project-URL: Source, https://gitlab.windenergy.dtu.dk/HAWC2/HAWC2Lib
Project-URL: Tracker, https://gitlab.windenergy.dtu.dk/HAWC2/HAWC2Lib/-/issues
Requires-Dist: numpy
Requires-Dist: intel-fortran-rt==2021.3.0
Requires-Dist: mkl==2021.3.0
Requires-Dist: multiclass_interface>=1.5
Provides-Extra: test
Requires-Dist: h2lib_tests; extra == "test"
Provides-Extra: mpi
Requires-Dist: mpi4py; extra == "mpi"
Dynamic: author
Dynamic: author-email
Dynamic: project-url
Dynamic: provides-extra
Dynamic: requires-dist
Dynamic: summary
